{
  "milestone": "reorder-btn-height",
  "capturedAt": "2026-02-11T13:26:20.740Z",
  "url": "http://localhost:4173",
  "scores": {
    "performance": 0.92,
    "accessibility": 1,
    "bestPractices": 1,
    "seo": 1
  },
  "metrics": {
    "firstContentfulPaint": {
      "value": 1457.979,
      "display": "1.5 s"
    },
    "largestContentfulPaint": {
      "value": 1646.979,
      "display": "1.6 s"
    },
    "totalBlockingTime": {
      "value": 328,
      "display": "330 ms"
    },
    "cumulativeLayoutShift": {
      "value": 0.038882138517618466,
      "display": "0.039"
    },
    "speedIndex": {
      "value": 2410.3340081226816,
      "display": "2.4 s"
    },
    "timeToInteractive": {
      "value": 1835.9790000000003,
      "display": "1.8 s"
    }
  }
}